[
  {
     "antiparasitario - antipulgas":[
        {
           "area":"antiparasitario - antipulgas",
           "name":"albex",
           "id":"8"
        },
        {
           "area":"antiparasitario - antipulgas",
           "name":"bravecto 10-20 kg",
           "id":"72"
        },
        {
           "area":"antiparasitario - antipulgas",
           "name":"bravecto 20-40 kg",
           "id":"73"
        },
        {
           "area":"antiparasitario - antipulgas",
           "name":"bravecto 2-4.5 kg",
           "id":"74"
        },
        {
           "area":"antiparasitario - antipulgas",
           "name":"bravecto 4.5-10 kg",
           "id":"75"
        },
        {
           "area":"antiparasitario - antipulgas",
           "name":"desparasitación",
           "id":"219"
        },
        {
           "area":"antiparasitario - antipulgas",
           "name":"desparasitación conejo",
           "id":"220"
        },
        {
           "area":"antiparasitario - antipulgas",
           "name":"meltra",
           "id":"424"
        },
        {
           "area":"antiparasitario - antipulgas",
           "name":"nexgard 2-4 kg",
           "id":"445"
        },
        {
           "area":"antiparasitario - antipulgas",
           "name":"nexgard 25-50 kg",
           "id":"446"
        },
        {
           "area":"antiparasitario - antipulgas",
           "name":"nexgart 4-10 kg",
           "id":"447"
        },
        {
           "area":"antiparasitario - antipulgas",
           "name":"power spot on 0-4 kg",
           "id":"584"
        },
        {
           "area":"antiparasitario - antipulgas",
           "name":"power spot on 4-8 kg",
           "id":"585"
        },
        {
           "area":"antiparasitario - antipulgas",
           "name":"power ultra 11-20 kg",
           "id":"586"
        },
        {
           "area":"antiparasitario - antipulgas",
           "name":"power ultra 21-40 kg",
           "id":"587"
        },
        {
           "area":"antiparasitario - antipulgas",
           "name":"power ultra 2-4 kg",
           "id":"588"
        },
        {
           "area":"antiparasitario - antipulgas",
           "name":"power ultra 41-60 kg",
           "id":"589"
        },
        {
           "area":"antiparasitario - antipulgas",
           "name":"power ultra 5-10 kg",
           "id":"590"
        },
        {
           "area":"antiparasitario - antipulgas",
           "name":"revolution 10-20 kg",
           "id":"628"
        },
        {
           "area":"antiparasitario - antipulgas",
           "name":"revolution 2.5-5 kg",
           "id":"629"
        },
        {
           "area":"antiparasitario - antipulgas",
           "name":"revolution 5-10 kg",
           "id":"630"
        },
        {
           "area":"antiparasitario - antipulgas",
           "name":"revolution hasta 2.5 kg",
           "id":"631"
        },
        {
           "area":"antiparasitario - antipulgas",
           "name":"revolution plus 2.5 - 5.0 kg",
           "id":"632"
        },
        {
           "area":"antiparasitario - antipulgas",
           "name":"revolution plus 5 - 10kg",
           "id":"633"
        },
        {
           "area":"antiparasitario - antipulgas",
           "name":"rivolta 2.5-7.5 kg",
           "id":"634"
        },
        {
           "area":"antiparasitario - antipulgas",
           "name":"simparica 1.3 - 2.5 kg",
           "id":"774"
        },
        {
           "area":"antiparasitario - antipulgas",
           "name":"simparica 10-20 kg",
           "id":"656"
        },
        {
           "area":"antiparasitario - antipulgas",
           "name":"simparica 2.5-5 kg",
           "id":"657"
        },
        {
           "area":"antiparasitario - antipulgas",
           "name":"simparica 20-40 kg",
           "id":"658"
        },
        {
           "area":"antiparasitario - antipulgas",
           "name":"simparica 5-10 kg",
           "id":"659"
        },
        {
           "area":"antiparasitario - antipulgas",
           "name":"simparica trio 10 - 20 kg",
           "id":"783"
        },
        {
           "area":"antiparasitario - antipulgas",
           "name":"simparica trio 2.5 - 5 kg",
           "id":"660"
        },
        {
           "area":"antiparasitario - antipulgas",
           "name":"simparica trio 20 - 40 kg",
           "id":"661"
        },
        {
           "area":"antiparasitario - antipulgas",
           "name":"simparica trio 5-10 kg",
           "id":"662"
        }
     ]
  },
  {
     "baño y peluqueria":[
        {
           "area":"baño y peluqueria",
           "name":"acondicionador",
           "id":"6"
        },
        {
           "area":"baño y peluqueria",
           "name":"baño acai (pequeño)",
           "id":"749"
        },
        {
           "area":"baño y peluqueria",
           "name":"baño antipulgas (grande)",
           "id":"27"
        },
        {
           "area":"baño y peluqueria",
           "name":"baño antipulgas (mediano)",
           "id":"28"
        },
        {
           "area":"baño y peluqueria",
           "name":"baño antipulgas (pequeño)",
           "id":"29"
        },
        {
           "area":"baño y peluqueria",
           "name":"baño chow chow",
           "id":"30"
        },
        {
           "area":"baño y peluqueria",
           "name":"baño con sanitraz (grande)",
           "id":"31"
        },
        {
           "area":"baño y peluqueria",
           "name":"baño con sanitraz (mediano)",
           "id":"32"
        },
        {
           "area":"baño y peluqueria",
           "name":"baño con sanitraz (pequeño)",
           "id":"33"
        },
        {
           "area":"baño y peluqueria",
           "name":"baño conejo",
           "id":"34"
        },
        {
           "area":"baño y peluqueria",
           "name":"baño extra grande",
           "id":"35"
        },
        {
           "area":"baño y peluqueria",
           "name":"baño gato adulto",
           "id":"36"
        },
        {
           "area":"baño y peluqueria",
           "name":"baño gato bebe",
           "id":"37"
        },
        {
           "area":"baño y peluqueria",
           "name":"baño grande",
           "id":"38"
        },
        {
           "area":"baño y peluqueria",
           "name":"baño keratina (grande)",
           "id":"39"
        },
        {
           "area":"baño y peluqueria",
           "name":"baño keratina (mediano)",
           "id":"40"
        },
        {
           "area":"baño y peluqueria",
           "name":"baño keratina (pequeño)",
           "id":"41"
        },
        {
           "area":"baño y peluqueria",
           "name":"baño mediano",
           "id":"42"
        },
        {
           "area":"baño y peluqueria",
           "name":"baño medicado (grande)",
           "id":"43"
        },
        {
           "area":"baño y peluqueria",
           "name":"baño medicado (mediano)",
           "id":"44"
        },
        {
           "area":"baño y peluqueria",
           "name":"baño medicado (pequeño)",
           "id":"45"
        },
        {
           "area":"baño y peluqueria",
           "name":"baño normal gran danes",
           "id":"46"
        },
        {
           "area":"baño y peluqueria",
           "name":"baño ovejero",
           "id":"47"
        },
        {
           "area":"baño y peluqueria",
           "name":"baño pastor",
           "id":"48"
        },
        {
           "area":"baño y peluqueria",
           "name":"baño pequeño",
           "id":"49"
        },
        {
           "area":"baño y peluqueria",
           "name":"baño samoyedo / siberiano",
           "id":"50"
        },
        {
           "area":"baño y peluqueria",
           "name":"baño tritohexidin (grande)",
           "id":"51"
        },
        {
           "area":"baño y peluqueria",
           "name":"baño tritohexidin (mediano)",
           "id":"52"
        },
        {
           "area":"baño y peluqueria",
           "name":"baño tritohexidin (pequeño)",
           "id":"53"
        },
        {
           "area":"baño y peluqueria",
           "name":"baño tropical acai (grande)",
           "id":"54"
        },
        {
           "area":"baño y peluqueria",
           "name":"baño tropical acai (mediano)",
           "id":"55"
        },
        {
           "area":"baño y peluqueria",
           "name":"baño tropical acai (pequeño)",
           "id":"56"
        },
        {
           "area":"baño y peluqueria",
           "name":"baño tropical pitanga (grande)",
           "id":"57"
        },
        {
           "area":"baño y peluqueria",
           "name":"baño tropical pitanga (mediano)",
           "id":"58"
        },
        {
           "area":"baño y peluqueria",
           "name":"baño tropical pitanga (pequeño)",
           "id":"59"
        },
        {
           "area":"baño y peluqueria",
           "name":"corte",
           "id":"187"
        },
        {
           "area":"baño y peluqueria",
           "name":"corte de uñas",
           "id":"188"
        },
        {
           "area":"baño y peluqueria",
           "name":"corte higiénico",
           "id":"189"
        },
        {
           "area":"baño y peluqueria",
           "name":"delivery",
           "id":"210"
        },
        {
           "area":"baño y peluqueria",
           "name":"delivery lejos",
           "id":"211"
        },
        {
           "area":"baño y peluqueria",
           "name":"depilacion de oidos",
           "id":"213"
        },
        {
           "area":"baño y peluqueria",
           "name":"desmotado",
           "id":"218"
        },
        {
           "area":"baño y peluqueria",
           "name":"hospedaje x dia",
           "id":"342"
        },
        {
           "area":"baño y peluqueria",
           "name":"hospedaje x horas",
           "id":"343"
        },
        {
           "area":"baño y peluqueria",
           "name":"limado de uñas eléctrico",
           "id":"403"
        },
        {
           "area":"baño y peluqueria",
           "name":"limpieza de oídos",
           "id":"407"
        },
        {
           "area":"baño y peluqueria",
           "name":"rapado",
           "id":"619"
        },
        {
           "area":"baño y peluqueria",
           "name":"retoque de cara",
           "id":"624"
        },
        {
           "area":"baño y peluqueria",
           "name":"retoque de patas",
           "id":"625"
        },
        {
           "area":"baño y peluqueria",
           "name":"tranquilizante",
           "id":"696"
        }
     ]
  },
  {
     "examenes":[
        {
           "area":"examenes",
           "name":"ecografia",
           "id":"230"
        },
        {
           "area":"examenes",
           "name":"radiografia 1 vista",
           "id":"617"
        },
        {
           "area":"examenes",
           "name":"radiografia 2 vistas",
           "id":"618"
        },
        {
           "area":"examenes",
           "name":"amilasa",
           "id":"10"
        },
        {
           "area":"examenes",
           "name":"anticonceptivo",
           "id":"14"
        },
        {
           "area":"examenes",
           "name":"bioquimica completa",
           "id":"67"
        },
        {
           "area":"examenes",
           "name":"citologia/biopsia por funcion",
           "id":"147"
        },
        {
           "area":"examenes",
           "name":"coprologico + antibiograma",
           "id":"182"
        },
        {
           "area":"examenes",
           "name":"coprologico completo",
           "id":"183"
        },
        {
           "area":"examenes",
           "name":"coprologico funcional",
           "id":"184"
        },
        {
           "area":"examenes",
           "name":"coprologico seriado (x3)",
           "id":"185"
        },
        {
           "area":"examenes",
           "name":"cortisol",
           "id":"190"
        },
        {
           "area":"examenes",
           "name":"cultivo de bacterias",
           "id":"198"
        },
        {
           "area":"examenes",
           "name":"descarte sanguineo de distemper",
           "id":"216"
        },
        {
           "area":"examenes",
           "name":"descarte sanguineo de parvovirus",
           "id":"217"
        },
        {
           "area":"examenes",
           "name":"electrolitos",
           "id":"232"
        },
        {
           "area":"examenes",
           "name":"examen coagulacion",
           "id":"254"
        },
        {
           "area":"examenes",
           "name":"examen tiroideo",
           "id":"255"
        },
        {
           "area":"examenes",
           "name":"gamma glutamil transpeptidasa (ggtp)",
           "id":"316"
        },
        {
           "area":"examenes",
           "name":"ggtp",
           "id":"753"
        },
        {
           "area":"examenes",
           "name":"glucosa",
           "id":"321"
        },
        {
           "area":"examenes",
           "name":"hemograma completo",
           "id":"328"
        },
        {
           "area":"examenes",
           "name":"histopalogia",
           "id":"341"
        },
        {
           "area":"examenes",
           "name":"lipasa",
           "id":"408"
        },
        {
           "area":"examenes",
           "name":"perfil hepatico",
           "id":"533"
        },
        {
           "area":"examenes",
           "name":"perfil lipidico",
           "id":"534"
        },
        {
           "area":"examenes",
           "name":"perfil microbiologico",
           "id":"535"
        },
        {
           "area":"examenes",
           "name":"perfil pancreatico",
           "id":"536"
        },
        {
           "area":"examenes",
           "name":"perfil renal",
           "id":"537"
        },
        {
           "area":"examenes",
           "name":"perfil tiroideo",
           "id":"538"
        },
        {
           "area":"examenes",
           "name":"pre anestesico",
           "id":"591"
        },
        {
           "area":"examenes",
           "name":"progesterona",
           "id":"600"
        },
        {
           "area":"examenes",
           "name":"snap 4dx (descarte de erlichia)",
           "id":"663"
        },
        {
           "area":"examenes",
           "name":"test distemper",
           "id":"680"
        },
        {
           "area":"examenes",
           "name":"test leucemia felina",
           "id":"681"
        },
        {
           "area":"examenes",
           "name":"test parvovirus",
           "id":"682"
        },
        {
           "area":"examenes",
           "name":"test schirmer",
           "id":"683"
        },
        {
           "area":"examenes",
           "name":"test sida felina",
           "id":"684"
        },
        {
           "area":"examenes",
           "name":"tricograma",
           "id":"700"
        },
        {
           "area":"examenes",
           "name":"tsh",
           "id":"703"
        },
        {
           "area":"examenes",
           "name":"urea",
           "id":"794"
        },
        {
           "area":"examenes",
           "name":"urianalisis",
           "id":"704"
        },
        {
           "area":"examenes",
           "name":"uroanalisis",
           "id":"707"
        },
        {
           "area":"examenes",
           "name":"urocultivo + antibiograma",
           "id":"708"
        }
     ]
  },
  {
     "servicios veterinarios":[
        {
           "area":"servicios veterinarios",
           "name":"abdominocentesis",
           "id":"5"
        },
        {
           "area":"servicios veterinarios",
           "name":"administración de medicamentos",
           "id":"7"
        },
        {
           "area":"servicios veterinarios",
           "name":"anestesia inhalatoria",
           "id":"11"
        },
        {
           "area":"servicios veterinarios",
           "name":"camara uci por hora",
           "id":"107"
        },
        {
           "area":"servicios veterinarios",
           "name":"castracion canino/felino",
           "id":"129"
        },
        {
           "area":"servicios veterinarios",
           "name":"certificado de salud",
           "id":"133"
        },
        {
           "area":"servicios veterinarios",
           "name":"certificado de vacunacion",
           "id":"134"
        },
        {
           "area":"servicios veterinarios",
           "name":"chip de identificación",
           "id":"136"
        },
        {
           "area":"servicios veterinarios",
           "name":"cistocentesis",
           "id":"146"
        },
        {
           "area":"servicios veterinarios",
           "name":"consulta especializada",
           "id":"179"
        },
        {
           "area":"servicios veterinarios",
           "name":"consulta general",
           "id":"180"
        },
        {
           "area":"servicios veterinarios",
           "name":"consulta noche",
           "id":"181"
        },
        {
           "area":"servicios veterinarios",
           "name":"control",
           "id":"797"
        },
        {
           "area":"servicios veterinarios",
           "name":"cremacion c/urna de cedro 1.5-5 kg",
           "id":"192"
        },
        {
           "area":"servicios veterinarios",
           "name":"cremacion c/urna de cedro 15.1-25 kg",
           "id":"193"
        },
        {
           "area":"servicios veterinarios",
           "name":"cremacion c/urna de cedro 25.1-35 kg",
           "id":"194"
        },
        {
           "area":"servicios veterinarios",
           "name":"cremacion c/urna de cedro 35.1-50 kg",
           "id":"195"
        },
        {
           "area":"servicios veterinarios",
           "name":"cremacion c/urna de cedro 5.1-15 kg",
           "id":"196"
        },
        {
           "area":"servicios veterinarios",
           "name":"cremacion c/urna de cedro hasta 1 kg",
           "id":"197"
        },
        {
           "area":"servicios veterinarios",
           "name":"curacion",
           "id":"199"
        },
        {
           "area":"servicios veterinarios",
           "name":"esterilizacion canino hembra",
           "id":"247"
        },
        {
           "area":"servicios veterinarios",
           "name":"esterilizacion felina hembra",
           "id":"784"
        },
        {
           "area":"servicios veterinarios",
           "name":"eutanasia",
           "id":"248"
        },
        {
           "area":"servicios veterinarios",
           "name":"evaluacion fisiovet",
           "id":"752"
        },
        {
           "area":"servicios veterinarios",
           "name":"evaluación terapia fisica",
           "id":"249"
        },
        {
           "area":"servicios veterinarios",
           "name":"extraccion de clavos con sedacion",
           "id":"256"
        },
        {
           "area":"servicios veterinarios",
           "name":"extraccion de uña sin sedacion",
           "id":"257"
        },
        {
           "area":"servicios veterinarios",
           "name":"fluidoterapia",
           "id":"297"
        },
        {
           "area":"servicios veterinarios",
           "name":"fluidoterapia / noche",
           "id":"298"
        },
        {
           "area":"servicios veterinarios",
           "name":"flushing vesical",
           "id":"299"
        },
        {
           "area":"servicios veterinarios",
           "name":"grapa sin sedación",
           "id":"779"
        },
        {
           "area":"servicios veterinarios",
           "name":"grapas con sedación",
           "id":"322"
        },
        {
           "area":"servicios veterinarios",
           "name":"internamiento x dia",
           "id":"348"
        },
        {
           "area":"servicios veterinarios",
           "name":"internamiento x noche",
           "id":"349"
        },
        {
           "area":"servicios veterinarios",
           "name":"intervención quirúrgica",
           "id":"350"
        },
        {
           "area":"servicios veterinarios",
           "name":"inyeccion 10 - 20 kg",
           "id":"352"
        },
        {
           "area":"servicios veterinarios",
           "name":"inyeccion hasta 10kg",
           "id":"353"
        },
        {
           "area":"servicios veterinarios",
           "name":"inyección más de 20kg",
           "id":"354"
        },
        {
           "area":"servicios veterinarios",
           "name":"manejo de dolor y analgesia en paciente geriátrico",
           "id":"413"
        },
        {
           "area":"servicios veterinarios",
           "name":"nebulizacion por hora",
           "id":"442"
        },
        {
           "area":"servicios veterinarios",
           "name":"oxigenoterapia por hora",
           "id":"455"
        },
        {
           "area":"servicios veterinarios",
           "name":"peritonitis infecciosa felina (pif)",
           "id":"539"
        },
        {
           "area":"servicios veterinarios",
           "name":"profilaxis",
           "id":"599"
        },
        {
           "area":"servicios veterinarios",
           "name":"punción guiada",
           "id":"613"
        },
        {
           "area":"servicios veterinarios",
           "name":"reconstitucion de fluidos",
           "id":"620"
        },
        {
           "area":"servicios veterinarios",
           "name":"retiro de grapa sin sedación",
           "id":"786"
        },
        {
           "area":"servicios veterinarios",
           "name":"retiro de puntos con sedacion",
           "id":"622"
        },
        {
           "area":"servicios veterinarios",
           "name":"retiro de puntos sin sedacion",
           "id":"623"
        },
        {
           "area":"servicios veterinarios",
           "name":"sedación",
           "id":"644"
        },
        {
           "area":"servicios veterinarios",
           "name":"sedación/noche",
           "id":"645"
        },
        {
           "area":"servicios veterinarios",
           "name":"sondaje uretral sin sedacion",
           "id":"668"
        },
        {
           "area":"servicios veterinarios",
           "name":"sutura con sedación",
           "id":"673"
        },
        {
           "area":"servicios veterinarios",
           "name":"sutura sin sedacion",
           "id":"787"
        },
        {
           "area":"servicios veterinarios",
           "name":"terapia fisica",
           "id":"679"
        },
        {
           "area":"servicios veterinarios",
           "name":"toracocentesis",
           "id":"796"
        },
        {
           "area":"servicios veterinarios",
           "name":"vendaje robert jones",
           "id":"712"
        }
     ]
  },
  {
     "vacunas":[
        {
           "area":"vacunas",
           "name":"biocan puppy",
           "id":"66"
        },
        {
           "area":"vacunas",
           "name":"felocell",
           "id":"295"
        },
        {
           "area":"vacunas",
           "name":"kc",
           "id":"399"
        },
        {
           "area":"vacunas",
           "name":"leucemia",
           "id":"402"
        },
        {
           "area":"vacunas",
           "name":"microsporum",
           "id":"430"
        },
        {
           "area":"vacunas",
           "name":"quintuple",
           "id":"615"
        },
        {
           "area":"vacunas",
           "name":"rabia",
           "id":"616"
        },
        {
           "area":"vacunas",
           "name":"sextuple",
           "id":"646"
        },
        {
           "area":"vacunas",
           "name":"tarjeta de vacunación",
           "id":"782"
        }
     ]
  }
]